helix_sdk/__init__.py
helix_sdk/cli.py
helix_sdk/compressor.py
helix_sdk/core.py
helix_sdk/dataset.py
helix_sdk/loader.py
helix_sdk/remote.py
src/__init__.py
src/api/__init__.py
src/api/sdk_docs.py
src/api/server.py
src/core/__init__.py
src/core/audio_materializer.py
src/core/auth.py
src/core/benchmarker.py
src/core/blueprint_validator.py
src/core/constants.py
src/core/constraint_validator.py
src/core/deduplicator.py
src/core/domain_adapter.py
src/core/edge_case_generator.py
src/core/enhancement_layers.py
src/core/forensics.py
src/core/hlx_codec.py
src/core/label_propagator.py
src/core/materializer.py
src/core/mesh_builder.py
src/core/pipeline.py
src/core/preview_generator.py
src/core/privacy_filter.py
src/core/resolution_engine.py
src/core/text_materializer.py
src/core/verification.py
src/core/video_materializer.py
src/extractors/__init__.py
src/extractors/anchors.py
src/extractors/audio_extractor.py
src/extractors/gemini_anchors.py
src/extractors/saliency.py
src/extractors/text_anchors.py
src/extractors/video_extractor.py
src/integrations/__init__.py
src/integrations/pytorch_dataset.py
src/schema/__init__.py
src/schema/blueprint.py
helix_sdk-1.0.3.dist-info/METADATA
helix_sdk-1.0.3.dist-info/WHEEL
helix_sdk-1.0.3.dist-info/entry_points.txt
helix_sdk-1.0.3.dist-info/top_level.txt
helix_sdk-1.0.3.dist-info/RECORD
