Metadata-Version: 2.4
Name: helix-sdk
Version: 1.0.3
Summary: Semantic image compression for AI training datasets
Author-email: HELIX Team <team@helix-codec.dev>
License: MIT
Project-URL: Homepage, https://github.com/DB0SZ1/PROJECT-HELIX
Project-URL: Documentation, https://github.com/DB0SZ1/PROJECT-HELIX#readme
Project-URL: Repository, https://github.com/DB0SZ1/PROJECT-HELIX.git
Project-URL: Issues, https://github.com/DB0SZ1/PROJECT-HELIX/issues
Keywords: image-compression,ai,machine-learning,deep-learning,pytorch,gemini,computer-vision,dataset,training
Classifier: Development Status :: 4 - Beta
Classifier: Intended Audience :: Developers
Classifier: Intended Audience :: Science/Research
Classifier: License :: OSI Approved :: MIT License
Classifier: Programming Language :: Python :: 3
Classifier: Programming Language :: Python :: 3.10
Classifier: Programming Language :: Python :: 3.11
Classifier: Programming Language :: Python :: 3.12
Classifier: Topic :: Scientific/Engineering :: Artificial Intelligence
Classifier: Topic :: Scientific/Engineering :: Image Processing
Classifier: Topic :: Multimedia :: Graphics :: Graphics Conversion
Requires-Python: >=3.10
Requires-Dist: numpy>=1.24.0
Requires-Dist: pillow>=9.0.0
Requires-Dist: httpx>=0.25.0
Requires-Dist: pydantic>=2.0.0
Requires-Dist: python-dotenv>=1.0.0
Provides-Extra: local
Requires-Dist: opencv-python>=4.8.0; extra == "local"
Requires-Dist: google-genai>=1.0.0; extra == "local"
Provides-Extra: ml
Requires-Dist: torch>=2.0.0; extra == "ml"
Requires-Dist: torchvision>=0.15.0; extra == "ml"
Provides-Extra: dev
Requires-Dist: pytest>=7.0.0; extra == "dev"
Requires-Dist: pytest-cov>=4.0.0; extra == "dev"
Requires-Dist: black>=23.0.0; extra == "dev"
Requires-Dist: ruff>=0.1.0; extra == "dev"
Provides-Extra: all
Requires-Dist: helix-sdk[dev,local,ml]; extra == "all"
